Workbook

Sheet Priorización de Requerimientos
A1: PLAN VIVO DE REQUISITOS — INGENIERÍA DE SOFTWARE II · V3 (CU-01 Gestionar Pedido + CU-02 Cobro y Cierre de Caja)
A2: Trazabilidad ISO/IEC/IEEE 29148 → Funcionalidad → Refinamiento → Product Backlog / Jira → Diseño → Código → Prueba · v0.3 · 19/10/2026
A4: ID Funcionalidad | B4: FUNCIONALIDAD | C4: Requisito de Negocio (BR) | D4: Requisito de Stakeholder (StR) | E4: Requisito del Sistema (SyR) | F4: Requisito del Software (SWR) | G4: Verificación | H4: Descripción | I4: Comentarios del cliente | J4: Aprobado | K4: Prioridad (calculada) | L4: Indispensable | M4: Esfuerzo | N4: Afecta la Arquitectura | O4: Complejidad | P4: Ambiguo | Q4: Completo | R4: Estable | S4: PBI / User Story | T4: Clave Jira | U4: Estado de refinamiento | V4: Versión | W4: Última actualización | X4: Tipo de requisito | Y4: Caso de uso | Z4: Componente de diseño | AA4: Código fuente (backend/src/main/java/co/edu/uniquindio/comanda, frontend/src/app) | AB4: Prueba | AC4: Estado de implementación
A5: F-01 | B5: Seleccionar mesa y consultar su pedido activo | C5: BR-01: El restaurante debe reducir los errores en la toma de pedidos eliminando la comanda en papel (necesidad §2.3, prioridad Alta). | D5: StR-01: El mesero necesita identificar rápidamente qué mesas están disponibles, ocupadas o reservadas y consultar el pedido activo de una mesa desde la tablet. | E5: SyR-01: El sistema deberá mostrar al mesero autenticado el estado de cada mesa (disponible, ocupada, reservada) y, al seleccionar una mesa, su pedido activo si existe. | F5: SWR-01: La interfaz IU-01 deberá presentar una cuadrícula de 4 columnas con una tarjeta por mesa, coloreada según su estado (disponible: verde claro; ocupada: rojo; seleccionada: verde oscuro) y actualizada en tiempo real por WebSocket; al tocar una tarjeta deberá cargar el detalle del pedido activo (platos, cantidades y estado) en menos de 2 s. | G5: Demostración + prueba funcional: con 3 mesas en estados distintos la tablet muestra el color correcto de cada una; al cambiar un estado desde otro dispositivo la tarjeta se actualiza sin recargar; al tocar una mesa ocupada se muestra su pedido activo. | H5: Pasos 1–2 del curso normal de CU-01 (el mesero selecciona la mesa y el sistema muestra su estado). Cubre la operación CONSULTAR del CRUD. Traza: RF-01, RF-15, RD-01, estados E-01 a E-03, IU-01. | I5: Responde a la necesidad 'Reducir errores en toma de pedidos' (Alta). Colores y distribución según mockup IU-01. | J5: Sí | K5: =IF(L5="Sí","Must",IF(M5+O5<=4,"Should","Could")) -> Must | L5: Sí | M5: 2 | N5: No | O5: 2 | P5: No | Q5: Sí | R5: Sí | S5: Como mesero, quiero ver el estado de todas las mesas y el pedido activo de la que seleccione, para atender sin confundir mesas ni pedidos. | T5: EBS-1 | U5: Refinado | V5: v0.1 | W5: 22/09/2026 | X5: Funcional | Y5: CU-01 | Z5: MesaController → MesaService → MesaRepository/PedidoRepository | AA5: mesa/MesaService.java; features/mesero | AB5: Prueba de humo (F-01) | AC5: Implementado
A6: F-02 | B6: Consultar menú disponible por categoría | C6: BR-01: El restaurante debe reducir los errores en la toma de pedidos eliminando la comanda en papel (necesidad §2.3, prioridad Alta). BR-03: El restaurante debe controlar en tiempo real el inventario de ingredientes para no ofrecer platos que no se pueden preparar (necesidad §2.3, prioridad Alta). | D6: StR-02: El mesero necesita ver solo los platos que realmente se pueden preparar, organizados por categoría, para ofrecerlos al cliente sin tener que preguntar a cocina. | E6: SyR-02: El sistema deberá mostrar el menú organizado por categorías y permitir seleccionar únicamente los platos activos cuyos ingredientes sean suficientes en el inventario. | F6: SWR-02: El software deberá calcular la disponibilidad de cada plato comparando las cantidades de su receta con el stock actual de cada ingrediente; los platos sin stock se mostrarán deshabilitados (no seleccionables), los suspendidos no se mostrarán, y las pestañas de categoría filtrarán el listado sin recargar la página. | G6: Prueba: configurar un plato cuyo ingrediente tenga stock menor a la cantidad de la receta → el plato aparece deshabilitado y no puede agregarse; un plato suspendido no aparece; cambiar de categoría filtra la lista correctamente. | H6: Paso 2 del curso normal de CU-01 (el sistema muestra el menú disponible). Traza: RF-01 (restricción: no se pueden seleccionar platos no disponibles), RF-03, RF-13, RD-02, IU-01. | I6: Responde a la necesidad 'Controlar inventario de ingredientes' (Alta). Coherente con el estado 'Sin stock' automático del mockup IU-04 y con RF-13 (un plato suspendido no aparece en el menú). | J6: Sí | K6: =IF(L6="Sí","Must",IF(M6+O6<=4,"Should","Could")) -> Must | L6: Sí | M6: 3 | N6: No | O6: 3 | P6: No | Q6: Sí | R6: Sí | S6: Como mesero, quiero ver el menú por categorías con solo los platos disponibles, para no ofrecer al cliente algo que la cocina no puede preparar. | T6: EBS-2 | U6: Refinado | V6: v0.1 | W6: 22/09/2026 | X6: Funcional | Y6: CU-01 | Z6: MenuService + ReglaDisponibilidad (Strategy) | AA6: menu/MenuService.java; menu/DisponibilidadPorReceta.java | AB6: CalculadoraRecetaTest; prueba de humo | AC6: Implementado
A7: F-03 | B7: Registrar pedido asociado a una mesa | C7: BR-01: El restaurante debe reducir los errores en la toma de pedidos eliminando la comanda en papel (necesidad §2.3, prioridad Alta). | D7: StR-03: El mesero necesita registrar digitalmente los platos que pide el cliente y asociarlos a su mesa, para evitar pedidos mal anotados o incompletos. | E7: SyR-03: El sistema deberá permitir al mesero autenticado crear un pedido para una mesa con uno o más platos activos y sus cantidades, registrando fecha, hora y mesero responsable. | F7: SWR-03: La operación crearPedido(numeroMesa, listaItems) deberá: validar la sesión con rol Mesero; rechazar el pedido si la lista está vacía o si la mesa está 'Ocupada' por otro pedido; crear el Pedido en estado 'Registrado' con la fecha y hora actual y un DetallePedido por ítem; y cambiar la mesa a 'Ocupada', todo en una única transacción. | G7: Pruebas unitarias y de integración sobre crearPedido: (a) pedido válido → Pedido 'Registrado', N DetallePedido y mesa 'Ocupada'; (b) lista vacía → error; (c) mesa ocupada → error; (d) usuario sin rol Mesero → acceso denegado (HTTP 403). | H7: Pasos 3–4 del curso normal de CU-01 y Contrato de operación 1 (crearPedido). Cubre la operación CREAR del CRUD. Traza: RF-01, RD-01, RD-02, RD-03, RNF-04, Diagrama de secuencia 1. | I7: Responde a la necesidad 'Reducir errores en toma de pedidos' (Alta). Sugerencia a validar: permitir observaciones por plato (p. ej. 'sin cebolla'), hoy no contempladas en el SyRS. | J7: Sí | K7: =IF(L7="Sí","Must",IF(M7+O7<=4,"Should","Could")) -> Must | L7: Sí | M7: 3 | N7: Sí | O7: 3 | P7: No | Q7: Sí | R7: Sí | S7: Como mesero, quiero registrar en la tablet los platos que pide el cliente y asociarlos a su mesa, para que el pedido quede completo y sin errores de escritura. | T7: EBS-3 | U7: Refinado | V7: v0.1 | W7: 22/09/2026 | X7: Funcional | Y7: CU-01 | Z7: PedidoService (Facade) · Contrato 1 | AA7: pedido/PedidoService.java#crearPedido | AB7: Prueba de humo (F-03, RD-01) | AC7: Implementado
A8: F-04 | B8: Modificar pedido antes de confirmarlo | C8: BR-01: El restaurante debe reducir los errores en la toma de pedidos eliminando la comanda en papel (necesidad §2.3, prioridad Alta). BR-05: El restaurante debe mejorar la experiencia del cliente con una atención más rápida y sin errores (necesidad §2.3, prioridad Media). | D8: StR-04: El mesero necesita agregar, quitar o cambiar la cantidad de platos cuando el cliente cambia de opinión antes de enviar el pedido a cocina. | E8: SyR-04: El sistema deberá permitir editar los ítems de un pedido (agregar, eliminar y cambiar cantidad) mientras no haya sido confirmado, recalculando el resumen del pedido. | F8: SWR-04: El pie de pantalla de IU-01 deberá mostrar el resumen del pedido en construcción con controles +/– y eliminar por ítem (botones de mínimo 44x44 px, RNF-03); cada cambio recalculará el subtotal en pantalla y, una vez confirmado el pedido, los controles de edición se deshabilitarán. | G8: Prueba: agregar 3 platos, cambiar la cantidad de uno y eliminar otro → el resumen muestra exactamente los 2 ítems restantes con el subtotal correcto; tras confirmar, los controles de edición no están disponibles. | H8: Curso alterno 3a de CU-01 (el cliente modifica el pedido antes de confirmarlo). Cubre la operación MODIFICAR del CRUD. Traza: RF-01, RF-06, RNF-03, IU-01. | I8: El SyRS solo contempla modificar antes de confirmar. Validar con el cliente si se necesita agregar platos a un pedido ya enviado a cocina (p. ej. un postre), lo que cambiaría esta funcionalidad. | J8: Sí | K8: =IF(L8="Sí","Must",IF(M8+O8<=4,"Should","Could")) -> Must | L8: Sí | M8: 2 | N8: No | O8: 2 | P8: No | Q8: Sí | R8: No | S8: Como mesero, quiero editar los platos del pedido antes de confirmarlo, para reflejar los cambios que pida el cliente sin empezar de nuevo. | T8: EBS-4 | U8: Refinado | V8: v0.1 | W8: 22/09/2026 | X8: Funcional | Y8: CU-01 | Z8: IU-01 resumen del pedido | AA8: features/mesero/mesero.component.ts | AB8: Prueba manual de interfaz | AC8: Implementado
A9: F-05 | B9: Validar disponibilidad de ingredientes al confirmar el pedido | C9: BR-03: El restaurante debe controlar en tiempo real el inventario de ingredientes para no ofrecer platos que no se pueden preparar (necesidad §2.3, prioridad Alta). | D9: StR-05: El mesero necesita saber, al confirmar, si algún plato ya no se puede preparar, para ofrecer una alternativa al cliente en ese mismo momento. | E9: SyR-05: El sistema deberá verificar de nuevo contra el inventario la disponibilidad de todos los platos del pedido al confirmarlo y, si alguno no está disponible, rechazar la confirmación indicando el plato afectado. | F9: SWR-05: Al confirmar, el backend deberá re-consultar el stock dentro de la misma transacción de registro, bloqueando los registros de los ingredientes afectados para que dos pedidos concurrentes no consuman el mismo stock; si la validación falla, responderá con la lista de platos no disponibles y la tablet mostrará una alerta sin perder los demás ítems del pedido. | G9: Prueba de concurrencia: dos tablets confirman al mismo tiempo pedidos que requieren el último stock de un ingrediente → solo uno se registra y el otro recibe la alerta con el plato afectado; el pedido rechazado conserva sus demás ítems. | H9: Paso 4 y curso alterno 4a de CU-01 (ingrediente no disponible al confirmar; el mesero propone un plato alternativo). Traza: RF-03 (restricción de concurrencia), RD-02. | I9: Responde a la necesidad 'Controlar inventario de ingredientes' (Alta). Según el SyRS, la alternativa la propone el mesero; no se exige sugerencia automática. | J9: Sí | K9: =IF(L9="Sí","Must",IF(M9+O9<=4,"Should","Could")) -> Must | L9: Sí | M9: 4 | N9: Sí | O9: 4 | P9: No | Q9: Sí | R9: Sí | S9: Como mesero, quiero que el sistema me avise al confirmar si un plato se quedó sin ingredientes, para ofrecerle otra opción al cliente de inmediato. | T9: EBS-5 | U9: Refinado | V9: v0.1 | W9: 22/09/2026 | X9: Funcional | Y9: CU-01 | Z9: ConsumoIngredientesPedido (Extract Class) · bloqueo pesimista | AA9: pedido/ConsumoIngredientesPedido.java#reservar | AB9: Prueba de humo (stock insuficiente) | AC9: Implementado
A10: F-06 | B10: Descontar ingredientes del inventario al confirmar el pedido | C10: BR-03: El restaurante debe controlar en tiempo real el inventario de ingredientes para no ofrecer platos que no se pueden preparar (necesidad §2.3, prioridad Alta). | D10: StR-06: El administrador necesita que el inventario se actualice automáticamente con cada pedido, para saber en todo momento qué ingredientes quedan. | E10: SyR-06: El sistema deberá descontar automáticamente del inventario, al confirmar el pedido, las cantidades de ingredientes definidas en la receta de cada plato multiplicadas por la cantidad pedida. | F10: SWR-06: El descuento deberá ejecutarse en la misma transacción que registra el pedido (si una de las dos operaciones falla, ninguna se guarda); después del descuento, si algún ingrediente queda en su nivel mínimo o por debajo, se emitirá el evento de alerta de inventario al panel de administración. | G10: Prueba de integración: pedido de 2 unidades de un plato cuya receta usa 150 g de arroz → el stock de arroz baja exactamente 300 g; al forzar un error después del descuento, ni el pedido ni el descuento quedan guardados; un ingrediente que cruza el mínimo genera la alerta. | H10: Paso 4 del curso normal de CU-01 ('el sistema registra el pedido y descuenta los ingredientes del inventario'). Traza: RF-05, RF-14. | I10: El descuento depende de las recetas configuradas por el administrador (CU-03 / CU-04). Queda por definir si al anular un pedido se reintegran los ingredientes (ver F-13). | J10: Sí | K10: =IF(L10="Sí","Must",IF(M10+O10<=4,"Should","Could")) -> Must | L10: Sí | M10: 3 | N10: Sí | O10: 3 | P10: No | Q10: Sí | R10: Sí | S10: Como administrador, quiero que cada pedido confirmado descuente sus ingredientes del inventario, para conocer el stock real sin conteos manuales. | T10: EBS-6 | U10: Refinado | V10: v0.1 | W10: 22/09/2026 | X10: Funcional | Y10: CU-01 | Z10: ConsumoIngredientesPedido.descontar · MovimientoInventario | AA10: pedido/ConsumoIngredientesPedido.java#descontar | AB10: CalculadoraRecetaTest | AC10: Implementado
A11: F-07 | B11: Enviar comanda a la pantalla de cocina en tiempo real | C11: BR-02: El restaurante debe agilizar la comunicación sala-cocina para reducir los tiempos de atención al cliente (necesidad §2.3, prioridad Alta). | D11: StR-07: El cocinero necesita recibir cada pedido confirmado en su pantalla de inmediato, sin depender de que el mesero lleve la comanda en papel. | E11: SyR-07: El sistema deberá enviar automáticamente la comanda a la pantalla de cocina al confirmarse el pedido, con número de mesa, platos, cantidades y hora de confirmación. | F11: SWR-07: El servidor deberá publicar un evento de pedido confirmado por WebSocket (IS-04) a los clientes de cocina suscritos; el tiempo entre la confirmación en la tablet y la visualización en la pantalla de cocina no deberá superar 2,0 s en la red Wi-Fi interna. | G11: Prueba de desempeño: 50 confirmaciones sobre la red Wi-Fi del restaurante midiendo el tiempo tablet → pantalla de cocina. Criterio: 100 % de comandas recibidas y tiempo máximo ≤ 2,0 s. | H11: Paso 4 (envío de la comanda) y paso 5 del curso normal de CU-01. Traza: RF-02, RNF-02, IS-04, §3.4 Interfaces de comunicación. | I11: Responde a la necesidad 'Agilizar comunicación sala-cocina' (Alta). RNF-02 está marcado como crítico. | J11: Sí | K11: =IF(L11="Sí","Must",IF(M11+O11<=4,"Should","Could")) -> Must | L11: Sí | M11: 4 | N11: Sí | O11: 4 | P11: No | Q11: Sí | R11: Sí | S11: Como cocinero, quiero recibir en mi pantalla cada pedido apenas se confirma, para empezar a prepararlo sin esperar la comanda en papel. | T11: EBS-7 | U11: Refinado | V11: v0.1 | W11: 22/09/2026 | X11: Funcional | Y11: CU-01 | Z11: Eventos + PublicadorTiempoReal (Observer) | AA11: tiemporeal/PublicadorTiempoReal.java | AB11: Prueba de humo (cocina) | AC11: Implementado
A12: F-08 | B12: Almacenar y reenviar comandas ante pérdida de conexión | C12: BR-04: El restaurante debe garantizar la continuidad de la operación y no perder pedidos ante fallas de conectividad (§3.4 Interfaces de comunicación). | D12: StR-08: El administrador necesita que ningún pedido se pierda si la red o la pantalla de cocina se desconectan durante el servicio. | E12: SyR-08: El sistema deberá almacenar las comandas que no puedan entregarse a la pantalla de cocina y reenviarlas automáticamente, en orden de confirmación, al restablecerse la conexión. | F12: SWR-08: Cada comanda confirmada quedará registrada en una cola persistente del servidor (tabla entrega_comanda, en la misma transacción del pedido) hasta que la pantalla de cocina confirme su recepción (ACK); las no confirmadas se reenviarán cada 5 s en orden de confirmación y sin duplicados (idempotencia por idPedido) mientras la cocina esté conectada, y al reconectarse la cocina recargará y confirmará todas. La tablet mostrará 'Cocina sin conexión · N comandas en cola' mientras dure la falla. Si es la tablet la que pierde la red, el pedido se guardará en el dispositivo y se reenviará con una clave de idempotencia para no duplicarlo. | G12: Prueba de resiliencia: desconectar la pantalla de cocina, confirmar 3 pedidos y reconectar → los 3 aparecen en orden de confirmación y sin duplicados; el indicador de conexión refleja la falla mientras dura. | H12: Modo M-03 'Sin conexión a cocina' y §3.4 (almacenar localmente y reenviar al restablecer la conexión), aplicado al paso 4 de CU-01. Traza: RF-02, M-03, IS-04. | I12: Conflicto RF-02 vs. M-03 resuelto en la reunión de validación (19/10/2026): prevalece M-03 / §3.4. Almacenamiento en el servidor (outbox con ACK) y, adicionalmente, cola local en la tablet. Se propone ajustar la redacción de RF-02. | J12: Sí | K12: =IF(L12="Sí","Must",IF(M12+O12<=4,"Should","Could")) -> Must | L12: Sí | M12: 5 | N12: Sí | O12: 5 | P12: No | Q12: Sí | R12: Sí | S12: Como administrador, quiero que las comandas se guarden y reenvíen automáticamente si se cae la conexión con cocina, para no perder pedidos en pleno servicio. | T12: EBS-8 | U12: Refinado | V12: v0.3 | W12: 19/10/2026 | X12: Funcional / Fiabilidad | Y12: CU-01 | Z12: ColaComandas + EntregaComanda (Outbox) + PresenciaCocina | AA12: cocina/ColaComandas.java; core/cola-pedidos.service.ts | AB12: ColaComandasTest; prueba de humo (idempotencia) | AC12: Implementado
A13: F-09 | B13: Visualizar comandas activas y tiempo en cola | C13: BR-02: El restaurante debe agilizar la comunicación sala-cocina para reducir los tiempos de atención al cliente (necesidad §2.3, prioridad Alta). | D13: StR-09: El cocinero necesita ver todas las comandas pendientes ordenadas por llegada y cuánto tiempo llevan esperando, para priorizar su preparación. | E13: SyR-09: El sistema deberá mostrar en la pantalla de cocina las comandas activas ordenadas por hora de llegada, con mesa, platos, estado de cada ítem y tiempo transcurrido desde la confirmación. | F13: SWR-09: IU-02 deberá presentar una tarjeta por comanda en cuadrícula de 3 columnas, con temporizador actualizado cada segundo y codificado por color (verde < 10 min; ámbar 10–15 min; rojo > 15 min), un punto de estado por ítem (ámbar: pendiente; verde: preparado) y una leyenda de colores; la vista no requerirá autenticación frecuente. | G13: Inspección de la interfaz contra el mockup IU-02 + prueba: simular comandas con 5, 12 y 20 minutos de antigüedad → se muestran en verde, ámbar y rojo respectivamente y en orden de llegada. | H13: Paso 5 del curso normal de CU-01 (el cocinero recibe la comanda en pantalla). Traza: RF-02 (cálculo del tiempo en cola), IU-02, IH-02. | I13: Diseño alineado al mockup IU-02, pensado para lectura a distancia en monitor o TV de cocina. | J13: Sí | K13: =IF(L13="Sí","Must",IF(M13+O13<=4,"Should","Could")) -> Must | L13: Sí | M13: 3 | N13: No | O13: 2 | P13: No | Q13: Sí | R13: Sí | S13: Como cocinero, quiero ver las comandas ordenadas por llegada y con su tiempo de espera, para preparar primero las más urgentes. | T13: EBS-9 | U13: Refinado | V13: v0.1 | W13: 22/09/2026 | X13: Funcional | Y13: CU-01 | Z13: IU-02 Pantalla de cocina | AA13: features/cocina/cocina.component.ts | AB13: Prueba manual de interfaz | AC13: Implementado
A14: F-10 | B14: Marcar plato / pedido como listo en cocina | C14: BR-02: El restaurante debe agilizar la comunicación sala-cocina para reducir los tiempos de atención al cliente (necesidad §2.3, prioridad Alta). | D14: StR-10: El cocinero necesita indicar con un solo toque cuándo un plato o pedido está listo, para que el mesero lo recoja sin demoras. | E14: SyR-10: El sistema deberá permitir al cocinero cambiar el estado del pedido (Registrado → En Preparación → Listo para Servir) y marcar ítems como preparados, respetando la secuencia de estados definida. | F14: SWR-10: La operación actualizarEstado(idPedido, nuevoEstado) deberá rechazar transiciones que no sigan la secuencia de RD-03 (sin saltos ni retrocesos); el botón 'Marcar como listo' deberá cambiar a 'Listo — notificado' y deshabilitarse tras la primera pulsación para evitar dobles envíos. | G14: Prueba unitaria de la máquina de estados: las transiciones válidas se aceptan; Registrado → Listo (salto) y Listo → En Preparación (retroceso) se rechazan; pulsar dos veces el botón genera un solo cambio de estado. | H14: Pasos 5–6 del curso normal de CU-01 y Contrato de operación 2 (actualizarEstado). Traza: RD-03, estados E-04 y E-05, Diagrama de secuencia 2, Diagrama de estados de Pedido. | I14: Decidido con el cliente: el estado 'En Preparación' lo marca el cocinero con el botón 'Iniciar preparación' (coincide con el Diagrama de secuencia 2). | J14: Sí | K14: =IF(L14="Sí","Must",IF(M14+O14<=4,"Should","Could")) -> Must | L14: Sí | M14: 3 | N14: No | O14: 3 | P14: No | Q14: Sí | R14: Sí | S14: Como cocinero, quiero marcar con un toque cuándo un plato está listo, para que el mesero sepa que debe recogerlo. | T14: EBS-10 | U14: Refinado | V14: v0.3 | W14: 19/10/2026 | X14: Funcional | Y14: CU-01 | Z14: EstadoPedido (máquina de estados) · Contrato 2 | AA14: pedido/EstadoPedido.java; pedido/Pedido.java | AB14: EstadoPedidoTest; prueba de humo (RD-03) | AC14: Implementado
A15: F-11 | B15: Notificar al mesero que el plato está listo | C15: BR-02: El restaurante debe agilizar la comunicación sala-cocina para reducir los tiempos de atención al cliente (necesidad §2.3, prioridad Alta). BR-05: El restaurante debe mejorar la experiencia del cliente con una atención más rápida y sin errores (necesidad §2.3, prioridad Media). | D15: StR-11: El mesero necesita enterarse en su tablet, sin ir a cocina, de que un plato de sus mesas está listo para servir. | E15: SyR-11: El sistema deberá notificar al mesero responsable cuando un plato de su pedido se marque como listo, indicando mesa y plato, y reenviar la alerta si no es atendida en 5 minutos. | F15: SWR-11: Al pasar un ítem o pedido a 'Listo para Servir', el servidor deberá enviar un evento WebSocket a la tablet del mesero asignado, que lo mostrará en la barra de notificación bajo el encabezado (mesa + descripción del plato); la notificación persistirá hasta que el mesero marque el plato como servido y se repetirá cada 5 minutos mientras no sea atendida. | G15: Prueba: marcar un plato como listo en cocina → la tablet del mesero asignado muestra la notificación con mesa y plato, y las demás tablets no la reciben; si no se atiende, la alerta se repite a los 5 minutos. | H15: Paso 6 y curso alterno 6a de CU-01 (reenvío de la alerta a los 5 minutos). Traza: RF-04, estado E-05, IU-01 (barra de notificación de plato listo). | I15: Cambio aplicado: la redacción de RF-04 se corrigió en el SyRS (la notificación ocurre cuando el plato se marca como LISTO, no como servido). | J15: Sí | K15: =IF(L15="Sí","Must",IF(M15+O15<=4,"Should","Could")) -> Must | L15: Sí | M15: 3 | N15: Sí | O15: 3 | P15: No | Q15: Sí | R15: Sí | S15: Como mesero, quiero recibir una notificación en la tablet cuando un plato de mis mesas esté listo, para servirlo caliente sin ir a preguntar a cocina. | T15: EBS-11 | U15: Refinado | V15: v0.3 | W15: 19/10/2026 | X15: Funcional | Y15: CU-01 | Z15: PedidoMapper.notificacion + RecordatorioPlatosListos | AA15: pedido/RecordatorioPlatosListos.java | AB15: Prueba de humo (notificación) | AC15: Implementado
A16: F-12 | B16: Marcar pedido como servido | C16: BR-05: El restaurante debe mejorar la experiencia del cliente con una atención más rápida y sin errores (necesidad §2.3, prioridad Media). | D16: StR-12: El mesero necesita registrar que entregó los platos, para cerrar la notificación y saber qué falta por servir. | E16: SyR-12: El sistema deberá permitir al mesero marcar como servido un plato o pedido en estado 'Listo para Servir', cambiándolo a 'Entregado' y retirando la notificación asociada. | F16: SWR-12: La acción 'Marcar como servido' de IU-01 solo estará habilitada para ítems en estado 'Listo para Servir'; al ejecutarla se registrará la hora de entrega y, cuando todos los ítems estén servidos, el pedido pasará a 'Entregado' y quedará disponible para cobro en el módulo de caja (IU-03). | G16: Prueba: marcar como servido un ítem listo → desaparece su notificación y se registra la hora; con todos los ítems servidos, el pedido queda 'Entregado' y aparece en la lista de mesas con cuenta del módulo de caja. | H16: Paso 7 del curso normal de CU-01 (el mesero recoge el plato y lo sirve). Traza: RF-04 (restricción), RD-03, RD-05, estado E-06. Es la entrada a CU-02 Cobro y Cierre de Caja. | I16: Cierra el flujo de CU-01 y habilita el cobro en CU-02. | J16: Sí | K16: =IF(L16="Sí","Must",IF(M16+O16<=4,"Should","Could")) -> Must | L16: Sí | M16: 2 | N16: No | O16: 2 | P16: No | Q16: Sí | R16: Sí | S16: Como mesero, quiero marcar los platos como servidos, para cerrar la notificación y dejar el pedido listo para cobrar. | T16: EBS-12 | U16: Refinado | V16: v0.1 | W16: 22/09/2026 | X16: Funcional | Y16: CU-01 | Z16: PedidoService.marcarServido | AA16: pedido/PedidoService.java#marcarServido | AB16: Prueba de humo | AC16: Implementado
... A25: F-21 | B25: Consultar inventario, alertas de mínimo y registrar entradas | C25: BR-03: El restaurante debe controlar en tiempo real el inventario de ingredientes para no ofrecer platos que no se pueden preparar (necesidad §2.3, prioridad Alta). | D25: StR-21: El administrador necesita ver el stock de cada ingrediente, enterarse cuando llega al mínimo y registrar la mercancía que llega. | E25: SyR-21: El sistema deberá listar los ingredientes con stock y nivel mínimo, alertar al administrador cuando un ingrediente llegue al mínimo y permitir registrar entradas de inventario. | F25: SWR-21: IU-04 mostrará la tabla de ingredientes con su estado (OK / Mínimo), la franja ámbar de alerta actualizada por /topic/inventario/alertas y un control para sumar una entrada mayor que cero, que quedará en movimiento_inventario con fecha, hora y usuario. | G25: Prueba: registrar una entrada de 500 g de chicharrón → el stock aumenta, el movimiento queda auditado y la alerta desaparece si supera el mínimo; cantidad 0 → rechazo. | H25: Pasos 1–4 y curso alterno 8a de CU-04 (alcance parcial). Traza: RF-14, RF-17 (parcial), IU-04. | I25: Falta registrar el proveedor y las pérdidas (RF-17) y crear ingredientes desde la interfaz (CU-04 pasos 5–8). | J25: Sí | K25: =IF(L25="Sí","Must",IF(M25+O25<=4,"Should","Could")) -> Should | L25: No | M25: 2 | N25: No | O25: 2 | P25: No | Q25: No | R25: Sí | S25: Como administrador, quiero ver el inventario con alertas y sumar las entradas de mercancía, para no quedarme sin ingredientes. | T25: EBS-21 | U25: Refinado | V25: v0.3 | W25: 19/10/2026 | X25: Funcional | Y25: CU-04 | Z25: InventarioService · IU-04 | AA25: inventario/InventarioService.java; features/admin | AB25: Prueba manual de interfaz | AC25: Implementado (parcial CU-04)
A27: Notas:
A28: • Esfuerzo y Complejidad en escala 1 (bajo) a 5 (alto), estimados por el equipo en el refinamiento.
A29: • Prioridad (calculada) = Must si es Indispensable; Should si Esfuerzo + Complejidad ≤ 4; en otro caso Could (criterio del equipo, ajustable).
A30: • Columnas en verde: trazabilidad hacia diseño, código y pruebas agregada en la V3 (pirámide BR → Feature → SWR → CU → Diseño → Código y pruebas).
A31: • Cambios de la V3: F-08, F-10, F-11 y F-13 pasan a 'Refinado' tras la validación con el cliente; se agregan F-14 a F-21 (CU-02 y CU-04 parcial).

Sheet Requisitos No Funcionales
A1: Requisitos no funcionales y atributos de calidad
A2: Clasificación según ISO/IEC 25010 · requisitos transversales del sistema
A4: ID | B4: Atributo de calidad (ISO/IEC 25010) | C4: Subcaracterística | D4: Requisito | E4: Métrica / criterio de aceptación | F4: Verificación | G4: Decisión de diseño / implementación | H4: Crítico | I4: Estado
A5: RNF-01 | B5: Seguridad | C5: Confidencialidad / Integridad | D5: Encriptar de extremo a extremo (HTTPS/TLS 1.3) todas las transmisiones hacia los servidores de la DIAN y la pasarela. | E5: 100 % del tráfico externo por TLS ≥ 1.2 (objetivo 1.3). | F5: Inspección de configuración del despliegue (Nginx/adaptadores). | G5: Los adaptadores externos son los únicos puntos de salida; TLS se termina en Nginx en producción. | H5: Sí | I5: Pendiente de despliegue
A6: RNF-02 | B6: Eficiencia de desempeño | C6: Comportamiento temporal | D6: La comanda debe llegar de la tablet a la pantalla de cocina en ≤ 2,0 s en la Wi-Fi interna. | E6: Percentil 100 ≤ 2,0 s en 50 envíos. | F6: Prueba de desempeño (SWR-07). | G6: WebSocket/STOMP con publicación inmediata tras el commit; broker en memoria. | H6: Sí | I6: Implementado (medición pendiente en el local)
A7: RNF-03 | B7: Usabilidad | C7: Accesibilidad / operabilidad | D7: Botones táctiles de mínimo 44 × 44 px y alto contraste en tablets. | E7: Todos los controles táctiles ≥ 44 px. | F7: Inspección de la interfaz. | G7: Tokens de diseño compartidos (styles.css) y min-height 44 px en botones. | H7: Sí | I7: Implementado
A8: RNF-04 | B8: Seguridad | C8: Autenticidad / responsabilidad | D8: Control de acceso basado en roles (RBAC): reportes y cierre de caja solo para Administrador y Cajero según el caso. | E8: Toda operación protegida responde 403 a un rol no autorizado; canal WebSocket autenticado. | F8: Prueba de humo (403) y PoliticaSuscripcionTest. | G8: JWT HS256; @PreAuthorize por operación; interceptor STOMP con permisos por tópico. | H8: Sí | I8: Implementado
A9: RNF-05 | B9: Fiabilidad | C9: Disponibilidad | D9: Disponibilidad del 99,5 % en el horario 11:00–22:00. | E9: ≤ 3,3 min de caída por día de operación. | F9: Monitoreo de /actuator/health. | G9: Contenedores con restart: unless-stopped; healthcheck de base de datos. | H9: Sí | I9: Parcial
A10: RNF-06 | B10: Portabilidad / Compatibilidad | C10: Adaptabilidad | D10: Plataforma 100 % responsive en las últimas versiones de Chrome y Safari. | E10: Vistas usables entre 360 px y 1920 px de ancho. | F10: Prueba manual en tablet y escritorio. | G10: Angular con CSS Grid/Flex y media queries. | H10: No | I10: Implementado
A11: RNF-07 | B11: Mantenibilidad | C11: Modularidad / analizabilidad / modificabilidad | D11: Arquitectura limpia y modular; API REST documentada. | E11: Swagger publicado; cobertura de pruebas reportada; principios SOLID en los módulos nuevos. | F11: Revisión de código + reporte JaCoCo en CI. | G11: Monolito modular por paquetes de dominio; patrones Strategy, Adapter, Facade, Observer, Builder. | H11: No | I11: Implementado
A12: RNF-08 | B12: Fiabilidad | C12: Tolerancia a fallos / recuperabilidad | D12: Ninguna comanda confirmada se pierde si cae la red o la pantalla de cocina (derivado de BR-04 y M-03). | E12: 0 comandas perdidas y 0 duplicadas en la prueba de resiliencia (SWR-08). | F12: ColaComandasTest + prueba de humo (idempotencia) + prueba manual de desconexión. | G12: Outbox con ACK y reenvío; cola local en la tablet con clave de idempotencia. | H12: Sí | I12: Implementado
A13: RNF-09 | B13: Seguridad | C13: Responsabilidad (no repudio) | D13: Toda anulación, movimiento de inventario, pago, factura y cierre registra usuario, fecha y hora (auditoría). | E13: 100 % de las operaciones sensibles con usuario y marca de tiempo. | F13: Inspección de la base de datos. | G13: Columnas de auditoría en pedido, movimiento_inventario, pago, factura y cierre_caja. | H13: No | I13: Implementado
A14: RNF-10 | B14: Fiabilidad | C14: Integridad de datos (consistencia transaccional) | D14: Pedido, descuento de inventario, factura y pagos se confirman o se deshacen juntos. | E14: Ningún estado intermedio visible tras una falla forzada. | F14: CajaServiceTest (reverso de tarjeta) y prueba de integración. | G14: Transacciones @Transactional, bloqueo pesimista y eventos AFTER_COMMIT. | H14: Sí | I14: Implementado

Sheet Interfaces y Restricciones
A1: Requisitos de interfaz y restricciones
A2: Hardware, software, comunicaciones y entorno de despliegue
A4: ID | B4: Tipo | C4: Elemento | D4: Requisito / restricción | E4: Protocolo / tecnología | F4: Implementación v0.3
A5: IU-01 | B5: Interfaz de usuario | C5: Tablet del mesero | D5: Seleccionar mesa, registrar platos y recibir notificación de plato listo. | E5: Angular · WebSocket | F5: features/mesero
A6: IU-02 | B6: Interfaz de usuario | C6: Pantalla de cocina | D6: Comandas por hora de llegada, temporizador y marcar listo. | E6: Angular · WebSocket | F6: features/cocina
A7: IU-03 | B7: Interfaz de usuario | C7: Módulo de caja | D7: Cuentas, desglose, método de pago y factura. | E7: Angular · REST | F7: features/caja (nuevo)
A8: IU-04 | B8: Interfaz de usuario | C8: Panel de administración | D8: Resumen, inventario con alertas y cierre de caja. | E8: Angular · REST · WebSocket | F8: features/admin (nuevo, parcial)
A9: IH-01 | B9: Hardware | C9: Tablet Android/iOS | D9: Navegador moderno y Wi-Fi. | E9: Chrome / Safari | F9: Responsive
A10: IH-02 | B10: Hardware | C10: Monitor/TV de cocina | D10: Lectura a distancia; navegador web. | E10: Chrome | F10: Tipografía grande y colores
A11: IH-03 | B11: Hardware | C11: Computador de caja | D11: Escritorio o portátil. | E11: Chrome / Safari | F11: IU-03 / IU-04
A12: IH-04 | B12: Hardware | C12: Router Wi-Fi | D12: Red local entre dispositivos. | E12: 802.11n o superior | F12: Restricción del entorno
A13: IH-05 | B13: Hardware | C13: Datáfono | D13: Pagos con tarjeta mediante la API del banco. | E13: API bancaria | F13: Adaptador PasarelaPago (simulado)
A14: IS-01 | B14: Software externo | C14: Pasarela de pago | D14: Autorizar y reversar transacciones con tarjeta. | E14: REST / HTTPS | F14: caja/pago/PasarelaPago (puerto) + PasarelaPagoSimulada
A15: IS-02 | B15: Software externo | C15: Servicio DIAN | D15: Validar facturas (CUFE) y recibir el reporte diario. | E15: SOAP / HTTPS | F15: caja/dian/ServicioFacturacionElectronica (puerto) + DianSimulada
... A21: RC-04 | B21: Restricción | C21: Datos de tarjetas | D21: No almacenar el número completo de la tarjeta (buenas prácticas PCI DSS). | E21: Solo últimos 4 dígitos | F21: Pago.ultimosDigitos

Sheet Matriz de Trazabilidad
A1: Matriz de trazabilidad: Requisitos de negocio (BR) × Funcionalidades (F)
A2: Una X indica que la funcionalidad responde al requisito de negocio. La última columna verifica completitud (ningún BR sin cubrir).
A4: Requisito de negocio | B4: F-01 | C4: F-02 | D4: F-03 | E4: F-04 | F4: F-05 | G4: F-06 | H4: F-07 | I4: F-08 | J4: F-09 | K4: F-10 | L4: F-11 | M4: F-12 | N4: F-13 | O4: F-14 | P4: F-15 | Q4: F-16 | R4: F-17 | S4: F-18 | T4: F-19 | U4: F-20 | V4: F-21 | W4: Funcionalidades que lo cubren
A5: BR-01: El restaurante debe reducir los errores en la toma de pedidos eliminando la comanda en papel (necesidad §2.3, prioridad Alta). | B5: X | C5: X | D5: X | E5: X | N5: X | W5: =COUNTIF(B5:V5,"X") -> 5
A6: BR-02: El restaurante debe agilizar la comunicación sala-cocina para reducir los tiempos de atención al cliente (necesidad §2.3, prioridad Alta). | H6: X | J6: X | K6: X | L6: X | W6: =COUNTIF(B6:V6,"X") -> 4
A7: BR-03: El restaurante debe controlar en tiempo real el inventario de ingredientes para no ofrecer platos que no se pueden preparar (necesidad §2.3, prioridad Alta). | C7: X | F7: X | G7: X | N7: X | V7: X | W7: =COUNTIF(B7:V7,"X") -> 5
A8: BR-04: El restaurante debe garantizar la continuidad de la operación y no perder pedidos ante fallas de conectividad (§3.4 Interfaces de comunicación). | I8: X | W8: =COUNTIF(B8:V8,"X") -> 1
A9: BR-05: El restaurante debe mejorar la experiencia del cliente con una atención más rápida y sin errores (necesidad §2.3, prioridad Media). | E9: X | L9: X | M9: X | O9: X | S9: X | W9: =COUNTIF(B9:V9,"X") -> 5
A10: BR-06: El restaurante debe eliminar los errores en el cobro calculando automáticamente la cuenta de cada mesa (necesidad §2.3, prioridad Alta). | O10: X | P10: X | Q10: X | R10: X | S10: X | W10: =COUNTIF(B10:V10,"X") -> 5
A11: BR-07: El restaurante debe cumplir la obligación de facturación electrónica de la DIAN en cada venta (necesidad §2.3, prioridad Alta; Resolución 000042 de 2020). | T11: X | W11: =COUNTIF(B11:V11,"X") -> 1
A12: BR-08: El restaurante debe generar el reporte de ventas diario y conciliar la caja sin sumas manuales (necesidad §2.3, prioridad Alta). | U12: X | W12: =COUNTIF(B12:V12,"X") -> 1
A13: Requisitos de negocio cubiertos por la funcionalidad | B13: =COUNTIF(B5:B12,"X") -> 1 | C13: =COUNTIF(C5:C12,"X") -> 2 | D13: =COUNTIF(D5:D12,"X") -> 1 | E13: =COUNTIF(E5:E12,"X") -> 2 | F13: =COUNTIF(F5:F12,"X") -> 1 | G13: =COUNTIF(G5:G12,"X") -> 1 | H13: =COUNTIF(H5:H12,"X") -> 1 | I13: =COUNTIF(I5:I12,"X") -> 1 | ... V13: =COUNTIF(V5:V12,"X") -> 1
A16: Pirámide de trazabilidad: BR → Feature → SWR → CU → Diseño → Código y pruebas
A17: Funcionalidad | B17: Requisito de negocio | C17: SWR | D17: Caso de uso | E17: Componente de diseño | F17: Código | G17: Prueba | H17: Jira
A18: F-01 Seleccionar mesa y consultar su pedido activo | B18: BR-01 | C18: SWR-01 | D18: CU-01 | E18: MesaController → MesaService → MesaRepository/PedidoRepository | F18: mesa/MesaService.java; features/mesero | G18: Prueba de humo (F-01) | H18: EBS-1
A19: F-02 Consultar menú disponible por categoría | B19: BR-01, BR-03 | C19: SWR-02 | D19: CU-01 | E19: MenuService + ReglaDisponibilidad (Strategy) | F19: menu/MenuService.java; menu/DisponibilidadPorReceta.java | G19: CalculadoraRecetaTest; prueba de humo | H19: EBS-2
A20: F-03 Registrar pedido asociado a una mesa | B20: BR-01 | C20: SWR-03 | D20: CU-01 | E20: PedidoService (Facade) · Contrato 1 | F20: pedido/PedidoService.java#crearPedido | G20: Prueba de humo (F-03, RD-01) | H20: EBS-3
A21: F-04 Modificar pedido antes de confirmarlo | B21: BR-01, BR-05 | C21: SWR-04 | D21: CU-01 | E21: IU-01 resumen del pedido | F21: features/mesero/mesero.component.ts | G21: Prueba manual de interfaz | H21: EBS-4
A22: F-05 Validar disponibilidad de ingredientes al confirmar el pedido | B22: BR-03 | C22: SWR-05 | D22: CU-01 | E22: ConsumoIngredientesPedido (Extract Class) · bloqueo pesimista | F22: pedido/ConsumoIngredientesPedido.java#reservar | G22: Prueba de humo (stock insuficiente) | H22: EBS-5
A23: F-06 Descontar ingredientes del inventario al confirmar el pedido | B23: BR-03 | C23: SWR-06 | D23: CU-01 | E23: ConsumoIngredientesPedido.descontar · MovimientoInventario | F23: pedido/ConsumoIngredientesPedido.java#descontar | G23: CalculadoraRecetaTest | H23: EBS-6
A24: F-07 Enviar comanda a la pantalla de cocina en tiempo real | B24: BR-02 | C24: SWR-07 | D24: CU-01 | E24: Eventos + PublicadorTiempoReal (Observer) | F24: tiemporeal/PublicadorTiempoReal.java | G24: Prueba de humo (cocina) | H24: EBS-7
A25: F-08 Almacenar y reenviar comandas ante pérdida de conexión | B25: BR-04 | C25: SWR-08 | D25: CU-01 | E25: ColaComandas + EntregaComanda (Outbox) + PresenciaCocina | F25: cocina/ColaComandas.java; core/cola-pedidos.service.ts | G25: ColaComandasTest; prueba de humo (idempotencia) | H25: EBS-8
A26: F-09 Visualizar comandas activas y tiempo en cola | B26: BR-02 | C26: SWR-09 | D26: CU-01 | E26: IU-02 Pantalla de cocina | F26: features/cocina/cocina.component.ts | G26: Prueba manual de interfaz | H26: EBS-9
A27: F-10 Marcar plato / pedido como listo en cocina | B27: BR-02 | C27: SWR-10 | D27: CU-01 | E27: EstadoPedido (máquina de estados) · Contrato 2 | F27: pedido/EstadoPedido.java; pedido/Pedido.java | G27: EstadoPedidoTest; prueba de humo (RD-03) | H27: EBS-10
A28: F-11 Notificar al mesero que el plato está listo | B28: BR-02, BR-05 | C28: SWR-11 | D28: CU-01 | E28: PedidoMapper.notificacion + RecordatorioPlatosListos | F28: pedido/RecordatorioPlatosListos.java | G28: Prueba de humo (notificación) | H28: EBS-11
... A38: F-21 Consultar inventario, alertas de mínimo y registrar entradas | B38: BR-03 | C38: SWR-21 | D38: CU-04 | E38: InventarioService · IU-04 | F38: inventario/InventarioService.java; features/admin | G38: Prueba manual de interfaz | H38: EBS-21

Sheet Actividades de IR
A1: Actividades de ingeniería de requisitos (extracción → análisis → especificación → validación)
A2: Registro de las actividades realizadas para llegar a la V3 del plan
A4: Actividad | B4: Técnica | C4: Participantes | D4: Artefactos producidos | E4: Resultado en la V3 | F4: Fecha
A5: Extracción (elicitación) | B5: Entrevista con el administrador y observación del proceso manual (comanda en papel, calculadora, cuaderno de caja); arqueología de documentos (Resolución DIAN 000042, Anexo Técnico). | C5: Administrador, cajero, mesero, equipo | D5: Necesidades §2.3 del Student Book; BR-01 a BR-08 | E5: Se identificaron las necesidades de cobro, facturación y cierre que originan CU-02. | F5: 22/09/2026
A6: Análisis | B6: Modelo de dominio, diagramas de estado, análisis de conflictos (RF-02 vs. M-03) y de compromisos (impuesto INC vs. IVA). | C6: Equipo | D6: Modelo de dominio, contratos 1–3, diagramas de estado | E6: Conflicto F-08 resuelto; decisión de impuesto documentada; estado Anulado agregado. | F6: 06/10/2026
A7: Especificación | B7: Plantilla SyRS (ISO/IEC/IEEE 29148): BR → StR → SyR → SWR por funcionalidad; historias de usuario en Jira. | C7: Equipo | D7: Este plan (hoja Priorización), SyRS, backlog EBS-1 a EBS-21 | E7: F-14 a F-21 especificadas con criterio de verificación. | F7: 13/10/2026
A8: Validación | B8: Revisión con el cliente (walkthrough de mockups y demostración del producto), checklist de calidad del requisito (ambiguo, completo, estable). | C8: Administrador, equipo | D8: Comentarios del cliente, estado de refinamiento | E8: F-08, F-10, F-11 y F-13 pasan a Refinado; F-04 sigue inestable (agregar platos a un pedido ya enviado). | F8: 19/10/2026
A9: Gestión de cambios | B9: Matriz de trazabilidad y control de versiones del plan (v0.1 → v0.3). | C9: Equipo | D9: Hojas Matriz de Trazabilidad e Historial | E9: Impacto de cada cambio identificado hasta el código y las pruebas. | F9: 19/10/2026

Sheet Resumen
A1: Resumen del plan de requisitos
A2: Indicadores calculados a partir de la hoja Priorización de Requerimientos
A4: Indicador | B4: Valor | C4: Fórmula / criterio
A5: Funcionalidades en el plan | B5: =COUNTA('Priorización de Requerimientos'!$A$5:$A$25) -> 21 | C5: Total de filas F-xx
A6: Aprobadas por el cliente | B6: =COUNTIF('Priorización de Requerimientos'!$J$5:$J$25,"Sí") -> 21 | C6: Aprobado = Sí
A7: Indispensables (Must) | B7: =COUNTIF('Priorización de Requerimientos'!$L$5:$L$25,"Sí") -> 18 | C7: Indispensable = Sí
A8: Refinadas | B8: =COUNTIF('Priorización de Requerimientos'!$U$5:$U$25,"Refinado") -> 21 | C8: Estado de refinamiento = Refinado
A9: En refinamiento / por refinar / cambio | B9: =B5-B8 -> 0 | C9: Funcionalidades − Refinadas
A10: Afectan la arquitectura | B10: =COUNTIF('Priorización de Requerimientos'!$N$5:$N$25,"Sí") -> 9 | C10: Afecta la Arquitectura = Sí
A11: Marcadas como ambiguas | B11: =COUNTIF('Priorización de Requerimientos'!$P$5:$P$25,"Sí") -> 0 | C11: Ambiguo = Sí
A12: Esfuerzo total (puntos) | B12: =SUM('Priorización de Requerimientos'!$M$5:$M$25) -> 61 | C12: Suma de Esfuerzo
A13: Esfuerzo CU-02 (puntos) | B13: =SUMIFS('Priorización de Requerimientos'!$M$5:$M$25,'Priorización de Requerimientos'!$Y$5:$Y$25,"CU-02*") -> 19 | C13: Suma de Esfuerzo con Caso de uso CU-02
A14: % refinadas | B14: =IFERROR(B8/B5,0) -> 1 | C14: Refinadas / Funcionalidades
A15: % aprobadas | B15: =IFERROR(B6/B5,0) -> 1 | C15: Aprobadas / Funcionalidades

Sheet Historial de Cambios
A1: Historial de cambios del plan
A2: Control de versiones
A4: Versión | B4: Fecha | C4: Autor | D4: Cambios
A5: v0.1 | B5: 22/09/2026 | C5: S. Lesmes · K. Puerta | D5: Primera versión: F-01 a F-13 del CU-01 con BR, StR, SyR, SWR, verificación y priorización.
A6: v0.2 | B6: 06/10/2026 | C6: S. Lesmes · K. Puerta | D6: Implementación de CU-01 en el repositorio; decisiones provisionales de F-08, F-10, F-11 y F-13 registradas en el README.
A7: v0.3 | B7: 19/10/2026 | C7: S. Lesmes · K. Puerta | D7: Validación con el cliente: F-08, F-10, F-11 y F-13 refinadas. Nuevas F-14 a F-21 (CU-02 Cobro y Cierre de Caja; CU-04 parcial). BR-06 a BR-08. Hojas nuevas: RNF (ISO 25010), Interfaces y restricciones, Matriz de trazabilidad, Actividades de IR y Resumen. Columnas de trazabilidad a diseño, código y pruebas.
